upvideo/__init__.py
upvideo/templates/upvideo/index.html
upvideo/templates/upvideo/nav.html
picbed_video-0.1.3.dist-info/LICENSE
picbed_video-0.1.3.dist-info/METADATA
picbed_video-0.1.3.dist-info/WHEEL
picbed_video-0.1.3.dist-info/top_level.txt
picbed_video-0.1.3.dist-info/RECORD
