Metadata-Version: 2.1
Name: picbed-video
Version: 0.1.3
Summary: Upload video to picbed
Home-page: https://github.com/staugur/picbed-video
Author: staugur
Author-email: staugur@saintic.com
License: BSD 3-Clause
Platform: UNKNOWN
